matlab2py/__init__.py
matlab2py/constants.py
matlab2py/conversions.py
matlab2py/debug.py
matlab2py/entry_point.py
matlab2py/figure_process.py
matlab2py/handles.py
matlab2py/helpers.py
matlab2py/matlab.py
matlab2py/singleton.py
matlab2py-0.0.1.dist-info/LICENSE
matlab2py-0.0.1.dist-info/METADATA
matlab2py-0.0.1.dist-info/WHEEL
matlab2py-0.0.1.dist-info/top_level.txt
matlab2py-0.0.1.dist-info/RECORD
